<?xml version="1.0" encoding="utf-8" ?><dwsync><file name="glyphicons-halflings-regular.eot" server="server.digisalad.cool" local="3533765600" remote="3542073480" Dst="-1" /><file name="glyphicons-halflings-regular.svg" server="server.digisalad.cool" local="3533765600" remote="3542073480" Dst="-1" /><file name="glyphicons-halflings-regular.woff" server="server.digisalad.cool" local="3533765600" remote="3542073480" Dst="-1" /><file name="glyphicons-halflings-regular.ttf" server="server.digisalad.cool" local="3533765600" remote="3542073480" Dst="-1" /><file name="glyphicons-halflings-regular.woff2" server="server.digisalad.cool" local="3533765600" remote="3542073480" Dst="-1" /><file name="glyphicons-halflings-regular.eot" server="server.digisalad.cool/sites/digisalad.cool/" local="3533765600" remote="3542091060" Dst="-1" /><file name="glyphicons-halflings-regular.svg" server="server.digisalad.cool/sites/digisalad.cool/" local="3533765600" remote="3542091060" Dst="-1" /><file name="glyphicons-halflings-regular.ttf" server="server.digisalad.cool/sites/digisalad.cool/" local="3533765600" remote="3542091060" Dst="-1" /><file name="glyphicons-halflings-regular.woff" server="server.digisalad.cool/sites/digisalad.cool/" local="3533765600" remote="3542091060" Dst="-1" /><file name="glyphicons-halflings-regular.woff2" server="server.digisalad.cool/sites/digisalad.cool/" local="3533765600" remote="3542091060" Dst="-1" /></dwsync>